yta_positioning/__init__.py
yta_positioning/coordinate.py
yta_positioning/map/__init__.py
yta_positioning/map/pair_of_coordinates.py
yta_positioning/position.py
yta_positioning/region.py
yta_positioning/utils.py
yta_positioning/validation.py
yta_positioning-0.0.7.dist-info/licenses/LICENSE
yta_positioning-0.0.7.dist-info/METADATA
yta_positioning-0.0.7.dist-info/WHEEL
yta_positioning-0.0.7.dist-info/RECORD
